{"type":"FeatureCollection", "features": [
{"type":"Feature","geometry":{"type":"Point","coordinates":[119.528434,50.73781]},"properties":{"ADCD":"150784210500103","PID":"1507842105001030f001","NAME":"七卡生产队安置点2","ADDRESS":"东南侧","LGTD":119.528434,"LTTD":50.73781,"REMARK":"位于村落东南侧，地势较高、平坦开阔，地质条件良好，能够容纳转移人口\r\n","dateStr":"2018-06-12 03:14:44","isPlot":1,"crtDate":"2018-06-02T00:00:00.000Z","crtUser":"admin","picPath":"","status":1,"cDefine1":"","POPULATION":253,"DBVER":"0f20180612031444205","RECORDMAN":"管理员(admin)#&#010-68781602","ZPID":"1507842105001030f00401","WSCD":"WAF1K00600000000"}},
{"type":"Feature","geometry":{"type":"Point","coordinates":[119.5183676,50.75014754]},"properties":{"ADCD":"150784210500103","PID":"1507842105001030f002","NAME":"安置点2","ADDRESS":"","LGTD":119.518368,"LTTD":50.750148,"REMARK":"\r\n","dateStr":"2018-06-02 15:30:57","isPlot":1,"crtDate":"2018-06-02T00:00:00.000Z","crtUser":"admin","picPath":"","status":0,"cDefine1":"","POPULATION":0,"DBVER":"0f20180603125845544","RECORDMAN":"管理员(admin)#&#010-68781602","ZPID":"","WSCD":"WAF1K00600000000"}},
{"type":"Feature","geometry":{"type":"Point","coordinates":[119.261158,50.463804]},"properties":{"ADCD":"150784101201101","PID":"1507841012011010f003","NAME":"五卡安置点1","ADDRESS":"村北","LGTD":119.261158,"LTTD":50.463804,"REMARK":"位于村落北侧，地势较高、平坦开阔，地质条件良好，能够容纳转移人口\r\n","dateStr":"2018-06-11 03:10:44","isPlot":1,"crtDate":"2018-06-02T00:00:00.000Z","crtUser":"admin","picPath":"","status":1,"cDefine1":"","POPULATION":31,"DBVER":"0f20180611031044280","RECORDMAN":"管理员(admin)#&#010-68781602","ZPID":"1507841012011010f00201","WSCD":"WAF0000003G00000"}},
{"type":"Feature","geometry":{"type":"Point","coordinates":[119.26197,50.451068]},"properties":{"ADCD":"150784101201101","PID":"1507841012011010f004","NAME":"五卡安置点2","ADDRESS":"村东","LGTD":119.26197,"LTTD":50.451068,"REMARK":"位于村落东侧，地势较高、平坦开阔，地质条件良好，能够容纳转移人口\r\n","dateStr":"2018-06-11 03:10:11","isPlot":1,"crtDate":"2018-06-02T00:00:00.000Z","crtUser":"admin","picPath":"","status":1,"cDefine1":"","POPULATION":2,"DBVER":"0f20180611031010453","RECORDMAN":"管理员(admin)#&#010-68781602","ZPID":"1507841012011010f00101","WSCD":"WAF0000003G00000"}},
{"type":"Feature","geometry":{"type":"Point","coordinates":[120.3371095,50.02618247]},"properties":{"ADCD":"150784400501000","PID":"1507844005010000f005","NAME":"安置点1","ADDRESS":"","LGTD":120.33711,"LTTD":50.026182,"REMARK":"\r\n","dateStr":"2018-06-02 16:24:00","isPlot":1,"crtDate":"2018-06-02T00:00:00.000Z","crtUser":"admin","picPath":"","status":0,"cDefine1":"","POPULATION":0,"DBVER":"0f20180603125129423","RECORDMAN":"管理员(admin)#&#010-68781602","ZPID":"","WSCD":"WAF150011VBE0000"}},
{"type":"Feature","geometry":{"type":"Point","coordinates":[120.329002,50.031663]},"properties":{"ADCD":"150784400501000","PID":"1507844005010000f006","NAME":"爱林屯（第二生产队）安置点","ADDRESS":"村西","LGTD":120.329002,"LTTD":50.031663,"REMARK":"位于村落西侧，地势较高、平坦开阔，地质条件良好，能够容纳转移人口\r\n","dateStr":"2018-06-13 17:06:25","isPlot":1,"crtDate":"2018-06-02T00:00:00.000Z","crtUser":"admin","picPath":"","status":1,"cDefine1":"","POPULATION":79,"DBVER":"2o20180613170625197","RECORDMAN":"管理员(admin)#&#010-68781602","ZPID":"1507844005010000f00301","WSCD":"WAF150011VBE0000"}},
{"type":"Feature","geometry":{"type":"Point","coordinates":[119.5680354794,50.3650774386]},"properties":{"ADCD":"150784403504000","PID":"1507844035040000f007","NAME":"安置点1","ADDRESS":"","LGTD":119.568035,"LTTD":50.365077,"REMARK":"\r\n","dateStr":"2018-06-03 13:14:10","isPlot":1,"crtDate":"2018-06-03T00:00:00.000Z","crtUser":"admin","picPath":"","status":0,"cDefine1":"","POPULATION":0,"DBVER":"0f20180603131717458","RECORDMAN":"管理员(admin)#&#010-68781602","ZPID":"","WSCD":"WAF16002v0000000"}},
{"type":"Feature","geometry":{"type":"Point","coordinates":[119.561392,50.360195]},"properties":{"ADCD":"150784403504000","PID":"1507844035040000f008","NAME":"红旗屯安置点2","ADDRESS":"西侧","LGTD":119.561392,"LTTD":50.360195,"REMARK":"位于村落西侧，地势较高、平坦开阔，地质条件良好，能够容纳转移人口\r\n","dateStr":"2018-06-12 04:04:54","isPlot":1,"crtDate":"2018-06-03T00:00:00.000Z","crtUser":"admin","picPath":"","status":1,"cDefine1":"","POPULATION":197,"DBVER":"0f20180612040453713","RECORDMAN":"管理员(admin)#&#010-68781602","ZPID":"1507844035040000f005","WSCD":"WAF16002v0000000"}},
{"type":"Feature","geometry":{"type":"Point","coordinates":[119.971798,51.415501]},"properties":{"ADCD":"150784211501100","PID":"1507842115011000f009","NAME":"临江村安置点","ADDRESS":"村北","LGTD":119.971798,"LTTD":51.415501,"REMARK":"位于村落北侧，地势较高、平坦开阔，地质条件良好，能够容纳转移人口\r\n","dateStr":"2018-06-12 03:16:35","isPlot":1,"crtDate":"2018-06-03T00:00:00.000Z","crtUser":"admin","picPath":"","status":1,"cDefine1":"","POPULATION":120,"DBVER":"0f20180612031634960","RECORDMAN":"管理员(admin)#&#010-68781602","ZPID":"1507842115011000f00601","WSCD":"WAF3V00300000000"}},
{"type":"Feature","geometry":{"type":"Point","coordinates":[120.51054,50.382368]},"properties":{"ADCD":"150784402505000","PID":"1507844025050000f00a","NAME":"安置点","ADDRESS":"村西","LGTD":120.51054,"LTTD":50.382368,"REMARK":"位于村落西侧，地势较高、平坦开阔，地质条件良好，能够容纳转移人口\r\n","dateStr":"2018-06-04 16:49:59","isPlot":1,"crtDate":"2018-06-04T00:00:00.000Z","crtUser":"admin","picPath":"","status":0,"cDefine1":"","POPULATION":47,"DBVER":"0f20180612042017805","RECORDMAN":"管理员(admin)#&#010-68781602","ZPID":"","WSCD":"WAF150061EB00000"}},
{"type":"Feature","geometry":{"type":"Point","coordinates":[120.545214,50.342533]},"properties":{"ADCD":"150784402501000","PID":"1507844025010000f00b","NAME":"白音扎拉噶屯（第二生产队）安置点","ADDRESS":"村南","LGTD":120.545214,"LTTD":50.342533,"REMARK":"位于村落南侧，地势较高、平坦开阔，地质条件良好，能够容纳转移人口\r\n","dateStr":"2018-06-12 03:55:23","isPlot":1,"crtDate":"2018-06-05T00:00:00.000Z","crtUser":"admin","picPath":"","status":1,"cDefine1":"","POPULATION":30,"DBVER":"0f20180612035523328","RECORDMAN":"管理员(admin)#&#010-68781602","ZPID":"1507844025010000f007","WSCD":"WAF150011GBG0000"}},
{"type":"Feature","geometry":{"type":"Point","coordinates":[120.331538,50.325802]},"properties":{"ADCD":"150784402504000","PID":"1507844025040000f00c","NAME":"小库力屯（第七生产队）安置点1","ADDRESS":"村南","LGTD":120.331538,"LTTD":50.325802,"REMARK":"位于村落南侧，地势较高、平坦开阔，地质条件良好，能够容纳转移人口\r\n","dateStr":"2018-06-12 03:57:40","isPlot":1,"crtDate":"2018-06-05T00:00:00.000Z","crtUser":"admin","picPath":"","status":1,"cDefine1":"","POPULATION":152,"DBVER":"0f20180612035740183","RECORDMAN":"管理员(admin)#&#010-68781602","ZPID":"1507844025040000f009","WSCD":"WAF1500A20000000"}},
{"type":"Feature","geometry":{"type":"Point","coordinates":[120.330872,50.337172]},"properties":{"ADCD":"150784402504000","PID":"1507844025040000f00d","NAME":"小库力屯（第七生产队）危安置点2","ADDRESS":"村北","LGTD":120.330872,"LTTD":50.337172,"REMARK":"位于村落北侧，地势较高、平坦开阔，地质条件良好，能够容纳转移人口\r\n","dateStr":"2018-06-11 12:50:23","isPlot":1,"crtDate":"2018-06-05T00:00:00.000Z","crtUser":"admin","picPath":"","status":1,"cDefine1":"","POPULATION":15,"DBVER":"0f20180611125022852","RECORDMAN":"管理员(admin)#&#010-68781602","ZPID":"1507844025040000f008","WSCD":"WAF150011KB00000"}},
{"type":"Feature","geometry":{"type":"Point","coordinates":[119.7633998047,51.1065423225]},"properties":{"ADCD":"150784211001000","PID":"1507842115010000f00e","NAME":"安置点","ADDRESS":"","LGTD":119.7634,"LTTD":51.106542,"REMARK":"\r\n","dateStr":"2018-06-05 14:29:17","isPlot":1,"crtDate":"2018-06-05T00:00:00.000Z","crtUser":"admin","picPath":"","status":0,"cDefine1":"","POPULATION":0,"DBVER":"0f20180605143004060","RECORDMAN":"管理员(admin)#&#010-68781602","ZPID":"","WSCD":"WAF0000004KAA000"}},
{"type":"Feature","geometry":{"type":"Point","coordinates":[120.0986853303,50.4631345061]},"properties":{"ADCD":"150784403506000","PID":"1507844035060000f00f","NAME":"安置点1","ADDRESS":"","LGTD":120.098685,"LTTD":50.463135,"REMARK":"\r\n","dateStr":"2018-06-05 15:37:11","isPlot":1,"crtDate":"2018-06-05T00:00:00.000Z","crtUser":"admin","picPath":"","status":0,"cDefine1":"","POPULATION":0,"DBVER":"0f20180605153741699","RECORDMAN":"管理员(admin)#&#010-68781602","ZPID":"","WSCD":"WAF16002n0000000"}},
{"type":"Feature","geometry":{"type":"Point","coordinates":[119.614922,50.692025]},"properties":{"ADCD":"150784210500102","PID":"1507842105001020f00g","NAME":"正阳生产队安置点","ADDRESS":"村东北居委会","LGTD":119.614922,"LTTD":50.692025,"REMARK":"位于村落东北侧，地势较高、平坦开阔，地质条件良好，能够容纳转移人口\r\n","dateStr":"2018-06-12 03:06:27","isPlot":1,"crtDate":"2018-06-06T00:00:00.000Z","crtUser":"admin","picPath":"","status":1,"cDefine1":"","POPULATION":220,"DBVER":"0f20180612030626732","RECORDMAN":"管理员(admin)#&#010-68781602","ZPID":"1507842105001020f00c02","WSCD":"WAF1K00200000000"}},
{"type":"Feature","geometry":{"type":"Point","coordinates":[120.4491874,50.2463365]},"properties":{"ADCD":"150784002201000","PID":"1507840022010000f00h","NAME":"安置点","ADDRESS":"","LGTD":120.449187,"LTTD":50.246336,"REMARK":"\r\n","dateStr":"2018-06-06 11:34:46","isPlot":1,"crtDate":"2018-06-06T00:00:00.000Z","crtUser":"admin","picPath":"","status":0,"cDefine1":"","POPULATION":25,"DBVER":"0f20180608084615614","RECORDMAN":"管理员(admin)#&#010-68781602","ZPID":"","WSCD":"WAF1550600000000"}},
{"type":"Feature","geometry":{"type":"Point","coordinates":[119.5680354794,50.3650774386]},"properties":{"ADCD":"150784403505000","PID":"1507844035050000f00i","NAME":"安置点1","ADDRESS":"","LGTD":119.568035,"LTTD":50.365077,"REMARK":"\r\n","dateStr":"2018-06-06 17:11:35","isPlot":1,"crtDate":"2018-06-06T00:00:00.000Z","crtUser":"admin","picPath":"","status":0,"cDefine1":"","POPULATION":0,"DBVER":"0f20180606171151343","RECORDMAN":"管理员(admin)#&#010-68781602","ZPID":"","WSCD":"WAF1610d00000000"}},
{"type":"Feature","geometry":{"type":"Point","coordinates":[119.55779427923088,50.363713087385385]},"properties":{"ADCD":"150784403504000","PID":"1507844035040000f00j","NAME":"安置点1","ADDRESS":"","LGTD":119.557794,"LTTD":50.363713,"REMARK":"\r\n","dateStr":"2018-06-06 17:12:23","isPlot":1,"crtDate":"2018-06-06T00:00:00.000Z","crtUser":"admin","picPath":"","status":0,"cDefine1":"","POPULATION":0,"DBVER":"0f20180606171229498","RECORDMAN":"管理员(admin)#&#010-68781602","ZPID":"","WSCD":"WAF16001w0000000"}},
{"type":"Feature","geometry":{"type":"Point","coordinates":[120.1228211486,50.4493238592]},"properties":{"ADCD":"150784401510000","PID":"1507844015090000f00k","NAME":"安置点","ADDRESS":"","LGTD":120.122821,"LTTD":50.449324,"REMARK":"\r\n","dateStr":"2018-06-06 17:42:07","isPlot":1,"crtDate":"2018-06-06T00:00:00.000Z","crtUser":"admin","picPath":"","status":0,"cDefine1":"","POPULATION":0,"DBVER":"0f20180606174248211","RECORDMAN":"管理员(admin)#&#010-68781602","ZPID":"","WSCD":"WAF16301I0000000"}},
{"type":"Feature","geometry":{"type":"Point","coordinates":[120.108461,50.443915]},"properties":{"ADCD":"150784401510000","PID":"1507844015090000f00l","NAME":"第四生产队安置点","ADDRESS":"村南","LGTD":120.108461,"LTTD":50.443915,"REMARK":"位于村落南侧，地势较高、平坦开阔，地质条件良好，能够容纳转移人口\r\n","dateStr":"2018-06-13 17:50:29","isPlot":1,"crtDate":"2018-06-06T00:00:00.000Z","crtUser":"admin","picPath":"","status":1,"cDefine1":"","POPULATION":46,"DBVER":"2o20180613175029216","RECORDMAN":"管理员(admin)#&#010-68781602","ZPID":"1507844015090000f00e01","WSCD":"WAF16301I0000000"}},
{"type":"Feature","geometry":{"type":"Point","coordinates":[120.078608,50.456382]},"properties":{"ADCD":"150784401509000","PID":"1507842000060000f00m","NAME":"第三生产队安置点1","ADDRESS":"村西","LGTD":120.078608,"LTTD":50.456382,"REMARK":"位于村落西侧，地势较高、平坦开阔，地质条件良好，能够容纳转移人口\r\n","dateStr":"2018-06-12 03:52:31","isPlot":1,"crtDate":"2018-06-07T00:00:00.000Z","crtUser":"admin","picPath":"","status":1,"cDefine1":"","POPULATION":216,"DBVER":"0f20180612035231172","RECORDMAN":"管理员(admin)#&#010-68781602","ZPID":"1507842000060000f00g01","WSCD":"WAF16301IA000000"}},
{"type":"Feature","geometry":{"type":"Point","coordinates":[120.09943298877295,50.463585246321784]},"properties":{"ADCD":"150784200005000","PID":"1507844015090000f00n","NAME":"安置点","ADDRESS":"村北","LGTD":120.099433,"LTTD":50.463585,"REMARK":"位于村落北侧，地势较高、平坦开阔，地质条件良好，能够容纳转移人口\r\n","dateStr":"2018-06-12 04:18:14","isPlot":1,"crtDate":"2018-06-07T00:00:00.000Z","crtUser":"admin","picPath":"","status":0,"cDefine1":"","POPULATION":25,"DBVER":"0f20180612041826609","RECORDMAN":"管理员(admin)#&#010-68781602","ZPID":"","WSCD":"WAF16301I0000000"}},
{"type":"Feature","geometry":{"type":"Point","coordinates":[120.179536,50.072691]},"properties":{"ADCD":"150784400507000","PID":"1507844005070000f00o","NAME":"南山屯（一0五生产队）安置点1","ADDRESS":"北侧","LGTD":120.179536,"LTTD":50.072691,"REMARK":"位于村落北侧，地势较高、平坦开阔，地质条件良好，能够容纳转移人口\r\n","dateStr":"2018-06-13 17:24:35","isPlot":1,"crtDate":"2018-06-07T00:00:00.000Z","crtUser":"admin","picPath":"","status":1,"cDefine1":"","POPULATION":187,"DBVER":"2o20180613172434654","RECORDMAN":"管理员(admin)#&#010-68781602","ZPID":"1507844005070000f00i01","WSCD":"WAF150021VBC0000"}},
{"type":"Feature","geometry":{"type":"Point","coordinates":[120.1761421414,50.0590691061]},"properties":{"ADCD":"150784400507000","PID":"1507844005070000f00p","NAME":"安置点1","ADDRESS":"","LGTD":120.176142,"LTTD":50.059069,"REMARK":"\r\n","dateStr":"2018-06-07 14:57:44","isPlot":1,"crtDate":"2018-06-07T00:00:00.000Z","crtUser":"admin","picPath":"","status":0,"cDefine1":"","POPULATION":0,"DBVER":"0f20180607150020031","RECORDMAN":"管理员(admin)#&#010-68781602","ZPID":"","WSCD":"WAF150021VBC0000"}},
{"type":"Feature","geometry":{"type":"Point","coordinates":[120.280918,51.500974]},"properties":{"ADCD":"150784103400101","PID":"1507841034001010f00q","NAME":"太平屯安置点1","ADDRESS":"北侧","LGTD":120.280918,"LTTD":51.500974,"REMARK":"位于村落北侧，地势较高、平坦开阔，地质条件良好，能够容纳转移人口\r\n","dateStr":"2018-06-13 17:34:37","isPlot":1,"crtDate":"2018-06-07T00:00:00.000Z","crtUser":"admin","picPath":"","status":1,"cDefine1":"","POPULATION":34,"DBVER":"2o20180613173437560","RECORDMAN":"管理员(admin)#&#010-68781602","ZPID":"1507841034001010f00j01","WSCD":"WAF17005T0000000"}},
{"type":"Feature","geometry":{"type":"Point","coordinates":[120.257389,51.503833]},"properties":{"ADCD":"150784103400100","PID":"1507841034001000f00r","NAME":"太平川安置点","ADDRESS":"北侧","LGTD":120.257389,"LTTD":51.503833,"REMARK":"位于村落北侧，地势较高、平坦开阔，地质条件良好，能够容纳转移人口\r\n","dateStr":"2018-06-12 02:51:29","isPlot":1,"crtDate":"2018-06-07T00:00:00.000Z","crtUser":"admin","picPath":"","status":1,"cDefine1":"","POPULATION":53,"DBVER":"0f20180612025129071","RECORDMAN":"管理员(admin)#&#010-68781602","ZPID":"1507841034001000f00k01","WSCD":"WAF1700M00000000"}},
{"type":"Feature","geometry":{"type":"Point","coordinates":[119.4961,50.210366]},"properties":{"ADCD":"150784101201102","PID":"1507841012010000f00s","NAME":"梁西村村委会安置点","ADDRESS":"南侧","LGTD":119.4961,"LTTD":50.210366,"REMARK":"位于村落南侧，地势较高、平坦开阔，地质条件良好，能够容纳转移人口\r\n","dateStr":"2018-06-12 02:51:54","isPlot":1,"crtDate":"2018-06-07T00:00:00.000Z","crtUser":"admin","picPath":"","status":1,"cDefine1":"","POPULATION":303,"DBVER":"0f20180612025153562","RECORDMAN":"管理员(admin)#&#010-68781602","ZPID":"1507841012010000f00l01","WSCD":"WAF1B00800000000"}},
{"type":"Feature","geometry":{"type":"Point","coordinates":[120.2589046983,50.6722604389]},"properties":{"ADCD":"150784401501000","PID":"1507844015010000f00t","NAME":"安置点","ADDRESS":"","LGTD":120.258905,"LTTD":50.67226,"REMARK":"\r\n","dateStr":"2018-06-07 18:09:41","isPlot":1,"crtDate":"2018-06-07T00:00:00.000Z","crtUser":"admin","picPath":"","status":0,"cDefine1":"","POPULATION":0,"DBVER":"0f20180608194818855","RECORDMAN":"管理员(admin)#&#010-68781602","ZPID":"","WSCD":"WAF1600S00000000"}},
{"type":"Feature","geometry":{"type":"Point","coordinates":[120.286788,50.025611]},"properties":{"ADCD":"150784400511000","PID":"1507844005110000f00u","NAME":"良种站村（第五生产队）安置点1","ADDRESS":"村东","LGTD":120.286788,"LTTD":50.025611,"REMARK":"位于村落东侧，地势较高、平坦开阔，地质条件良好，能够容纳转移人口\r\n","dateStr":"2018-06-13 17:12:02","isPlot":1,"crtDate":"2018-06-07T00:00:00.000Z","crtUser":"admin","picPath":"","status":1,"cDefine1":"","POPULATION":108,"DBVER":"2o20180613171201914","RECORDMAN":"管理员(admin)#&#010-68781602","ZPID":"1507844005110000f00m02","WSCD":"WAF150011VB00000"}},
{"type":"Feature","geometry":{"type":"Point","coordinates":[120.373126,50.090937]},"properties":{"ADCD":"150784400510000","PID":"1507844005100000f00v","NAME":"新力屯安置点","ADDRESS":"村东","LGTD":120.373126,"LTTD":50.090937,"REMARK":"位于村落东侧，地势较高、平坦开阔，地质条件良好，能够容纳转移人口\r\n","dateStr":"2018-06-12 03:30:25","isPlot":1,"crtDate":"2018-06-07T00:00:00.000Z","crtUser":"admin","picPath":"","status":1,"cDefine1":"","POPULATION":116,"DBVER":"0f20180612033024545","RECORDMAN":"管理员(admin)#&#010-68781602","ZPID":"1507844005100000f00n01","WSCD":"WAF150031VBE0000"}},
{"type":"Feature","geometry":{"type":"Point","coordinates":[120.115263,50.228189]},"properties":{"ADCD":"150784400502000","PID":"1507844005020000f00w","NAME":"安置点","ADDRESS":"村南","LGTD":120.115263,"LTTD":50.228189,"REMARK":"位于村落南侧，地势较高、平坦开阔，地质条件良好，能够容纳转移人口\r\n","dateStr":"2018-06-07 21:14:27","isPlot":1,"crtDate":"2018-06-07T00:00:00.000Z","crtUser":"admin","picPath":"","status":0,"cDefine1":"","POPULATION":22,"DBVER":"0f20180611031521806","RECORDMAN":"管理员(admin)#&#010-68781602","ZPID":"","WSCD":"WAF150071VB00000"}},
{"type":"Feature","geometry":{"type":"Point","coordinates":[120.115047,50.231055]},"properties":{"ADCD":"150784400502000","PID":"1507844005020000f00x","NAME":"大西山屯（第三生产队）安置点","ADDRESS":"村南","LGTD":120.115047,"LTTD":50.231055,"REMARK":"位于村落南侧，地势较高、平坦开阔，地质条件良好，能够容纳转移人口\r\n","dateStr":"2018-06-11 03:17:37","isPlot":1,"crtDate":"2018-06-07T00:00:00.000Z","crtUser":"admin","picPath":"","status":1,"cDefine1":"","POPULATION":43,"DBVER":"0f20180611031736786","RECORDMAN":"管理员(admin)#&#010-68781602","ZPID":"1507844005020000f00p01","WSCD":"WAF150071VB00000"}},
{"type":"Feature","geometry":{"type":"Point","coordinates":[119.912261,50.817693]},"properties":{"ADCD":"150784210001000","PID":"1507842100010000f00y","NAME":"噶拉湾社区安置点","ADDRESS":"村南","LGTD":119.912261,"LTTD":50.817693,"REMARK":"位于村落南侧，地势较高、平坦开阔，地质条件良好，能够容纳转移人口\r\n","dateStr":"2018-06-11 03:00:13","isPlot":1,"crtDate":"2018-06-07T00:00:00.000Z","crtUser":"admin","picPath":"","status":1,"cDefine1":"","POPULATION":32,"DBVER":"0f20180611030012851","RECORDMAN":"管理员(admin)#&#010-68781602","ZPID":"1507842105000000f00q01","WSCD":"WAF1610G00000000"}},
{"type":"Feature","geometry":{"type":"Point","coordinates":[119.80879,50.700696]},"properties":{"ADCD":"150784210500101","PID":"1507842105001010f00z","NAME":"向阳生产队安置点","ADDRESS":"村北","LGTD":119.80879,"LTTD":50.700696,"REMARK":"位于村落北侧，地势较高、平坦开阔，地质条件良好，能够容纳转移人口\r\n","dateStr":"2018-06-11 02:54:01","isPlot":1,"crtDate":"2018-06-07T00:00:00.000Z","crtUser":"admin","picPath":"","status":1,"cDefine1":"","POPULATION":26,"DBVER":"0f20180611025400748","RECORDMAN":"管理员(admin)#&#010-68781602","ZPID":"1507842105001010f00r01","WSCD":"WAF1610R00000000"}},
{"type":"Feature","geometry":{"type":"Point","coordinates":[119.525694,50.893429]},"properties":{"ADCD":"150784210500104","PID":"1507842105001040f00A","NAME":"八卡生产队安置点","ADDRESS":"村东","LGTD":119.525694,"LTTD":50.893429,"REMARK":"位于村落东侧，地势较高、平坦开阔，地质条件良好，能够容纳转移人口\r\n","dateStr":"2018-06-11 02:51:27","isPlot":1,"crtDate":"2018-06-07T00:00:00.000Z","crtUser":"admin","picPath":"","status":1,"cDefine1":"","POPULATION":45,"DBVER":"0f20180611025127332","RECORDMAN":"管理员(admin)#&#010-68781602","ZPID":"1507842105001040f00s01","WSCD":"WAF00000034i0000"}},
{"type":"Feature","geometry":{"type":"Point","coordinates":[119.880336,50.737274]},"properties":{"ADCD":"150784210500100","PID":"1507842105001000f00B","NAME":"朝阳生产队安置点","ADDRESS":"村东","LGTD":119.880336,"LTTD":50.737274,"REMARK":"位于村落东侧，地势较高、平坦开阔，地质条件良好，能够容纳转移人口\r\n","dateStr":"2018-06-10 20:08:53","isPlot":1,"crtDate":"2018-06-07T00:00:00.000Z","crtUser":"admin","picPath":"","status":1,"cDefine1":"","POPULATION":37,"DBVER":"0f20180610200852788","RECORDMAN":"管理员(admin)#&#010-68781602","ZPID":"1507842105001000f00t01","WSCD":"WAF1610M00000000"}},
{"type":"Feature","geometry":{"type":"Point","coordinates":[120.753707,51.258894]},"properties":{"ADCD":"150784103014000","PID":"1507841030140000f00C","NAME":"枫林社区安置点","ADDRESS":"村西","LGTD":120.753707,"LTTD":51.258894,"REMARK":"位于村落西侧，地势较高、平坦开阔，地质条件良好，能够容纳转移人口\r\n","dateStr":"2018-06-11 04:02:40","isPlot":1,"crtDate":"2018-06-07T00:00:00.000Z","crtUser":"admin","picPath":"","status":1,"cDefine1":"","POPULATION":577,"DBVER":"0f20180611040239687","RECORDMAN":"管理员(admin)#&#010-68781602","ZPID":"1507841030140000f00u01","WSCD":"WAF1700700000000"}},
{"type":"Feature","geometry":{"type":"Point","coordinates":[119.566046,50.217507]},"properties":{"ADCD":"150784101200100","PID":"1506271022080000f00D","NAME":"噶密山安置点","ADDRESS":"村北","LGTD":119.566046,"LTTD":50.217507,"REMARK":"位于村落北侧，地势较高、平坦开阔，地质条件良好，能够容纳转移人口\r\n","dateStr":"2018-06-11 03:01:20","isPlot":1,"crtDate":"2018-06-07T00:00:00.000Z","crtUser":"admin","picPath":"","status":1,"cDefine1":"","POPULATION":22,"DBVER":"0f20180611030119682","RECORDMAN":"管理员(admin)#&#010-68781602","ZPID":"1506271022080000f00v01","WSCD":"WAF1B00700000000"}},
{"type":"Feature","geometry":{"type":"Point","coordinates":[119.566103,50.217392]},"properties":{"ADCD":"150784101200100","PID":"1507841012000000f00E","NAME":"安置点","ADDRESS":"","LGTD":119.566103,"LTTD":50.217392,"REMARK":"\r\n","dateStr":"2018-06-07 23:44:36","isPlot":1,"crtDate":"2018-06-07T00:00:00.000Z","crtUser":"admin","picPath":"","status":0,"cDefine1":"","POPULATION":0,"DBVER":"0f20180607234452560","RECORDMAN":"管理员(admin)#&#010-68781602","ZPID":"","WSCD":"WAF1B00700000000"}},
{"type":"Feature","geometry":{"type":"Point","coordinates":[119.395652,50.334848]},"properties":{"ADCD":"150784101201100","PID":"1507841012011000f00F","NAME":"小河子安置点","ADDRESS":"村南","LGTD":119.395652,"LTTD":50.334848,"REMARK":"位于村落南侧，地势较高、平坦开阔，地质条件良好，能够容纳转移人口\r\n","dateStr":"2018-06-11 03:11:13","isPlot":1,"crtDate":"2018-06-07T00:00:00.000Z","crtUser":"admin","picPath":"","status":1,"cDefine1":"","POPULATION":8,"DBVER":"0f20180611031113291","RECORDMAN":"管理员(admin)#&#010-68781602","ZPID":"1507841012011000f00w01","WSCD":"WAF00000031C0000"}},
{"type":"Feature","geometry":{"type":"Point","coordinates":[120.173724,50.174733]},"properties":{"ADCD":"150784400500000","PID":"1507844005000000f00G","NAME":"葫芦头屯（第一生产队）安置点2","ADDRESS":"村西南","LGTD":120.173724,"LTTD":50.174733,"REMARK":"位于村落西南侧，地势较高、平坦开阔，地质条件良好，能够容纳转移人口\r\n","dateStr":"2018-06-11 03:21:26","isPlot":1,"crtDate":"2018-06-08T00:00:00.000Z","crtUser":"admin","picPath":"","status":1,"cDefine1":"","POPULATION":59,"DBVER":"0f20180611032126104","RECORDMAN":"管理员(admin)#&#010-68781602","ZPID":"1507844005000000f00y01","WSCD":"WAF150071VB00000"}},
{"type":"Feature","geometry":{"type":"Point","coordinates":[120.169698,50.181262]},"properties":{"ADCD":"150784400500000","PID":"1507844005000000f00H","NAME":"葫芦头屯（第一生产队）安置点1","ADDRESS":"村西","LGTD":120.169698,"LTTD":50.181262,"REMARK":"沿村内道路向村西侧开阔地转移\r\n","dateStr":"2018-06-13 17:08:36","isPlot":1,"crtDate":"2018-06-08T00:00:00.000Z","crtUser":"admin","picPath":"","status":1,"cDefine1":"","POPULATION":64,"DBVER":"2o20180613170836106","RECORDMAN":"管理员(admin)#&#010-68781602","ZPID":"1507844005000000f00x01","WSCD":"WAF150071VB00000"}},
{"type":"Feature","geometry":{"type":"Point","coordinates":[119.851533,50.465603]},"properties":{"ADCD":"150784403500000","PID":"1507844035000000f00I","NAME":"机耕屯安置点","ADDRESS":"村东南","LGTD":119.851533,"LTTD":50.465603,"REMARK":"位于村落东南侧，地势较高、平坦开阔，地质条件良好，能够容纳转移人口\r\n","dateStr":"2018-06-11 13:08:42","isPlot":1,"crtDate":"2018-06-08T00:00:00.000Z","crtUser":"admin","picPath":"","status":1,"cDefine1":"","POPULATION":75,"DBVER":"0f20180611130841901","RECORDMAN":"管理员(admin)#&#010-68781602","ZPID":"1507844035000000f00z","WSCD":"WAF1630E00000000"}},
{"type":"Feature","geometry":{"type":"Point","coordinates":[119.827097,50.509762]},"properties":{"ADCD":"150784403501000","PID":"1507844035010000f00J","NAME":"建设屯安置点","ADDRESS":"村西","LGTD":119.827097,"LTTD":50.509762,"REMARK":"位于村落西侧，地势较高、平坦开阔，地质条件良好，能够容纳转移人口\r\n","dateStr":"2018-06-11 13:09:18","isPlot":1,"crtDate":"2018-06-08T00:00:00.000Z","crtUser":"admin","picPath":"","status":1,"cDefine1":"","POPULATION":126,"DBVER":"0f20180611130917631","RECORDMAN":"管理员(admin)#&#010-68781602","ZPID":"1507844035010000f00A","WSCD":"WAF1600g00000000"}},
{"type":"Feature","geometry":{"type":"Point","coordinates":[120.19386,50.097644]},"properties":{"ADCD":"150784400508000","PID":"1507844005080000f00K","NAME":"坤库力村（110生产队）安置点","ADDRESS":"村西","LGTD":120.19386,"LTTD":50.097644,"REMARK":"位于村落西侧，地势较高、平坦开阔，地质条件良好，能够容纳转移人口\r\n","dateStr":"2018-06-13 17:10:17","isPlot":1,"crtDate":"2018-06-08T00:00:00.000Z","crtUser":"admin","picPath":"","status":1,"cDefine1":"","POPULATION":52,"DBVER":"2o20180613171017043","RECORDMAN":"管理员(admin)#&#010-68781602","ZPID":"1507844005080000f00B01","WSCD":"WAF150041VB00000"}},
{"type":"Feature","geometry":{"type":"Point","coordinates":[120.266804,50.166967]},"properties":{"ADCD":"150784400509000","PID":"1507844005090000f00L","NAME":"那尔莫格其屯（一二○生产队）安置点","ADDRESS":"村东","LGTD":120.266804,"LTTD":50.166967,"REMARK":"位于村落东侧，地势较高、平坦开阔，地质条件良好，能够容纳转移人口\r\n","dateStr":"2018-06-11 03:44:42","isPlot":1,"crtDate":"2018-06-08T00:00:00.000Z","crtUser":"admin","picPath":"","status":1,"cDefine1":"","POPULATION":12,"DBVER":"0f20180611034441545","RECORDMAN":"管理员(admin)#&#010-68781602","ZPID":"1507844005090000f00D01","WSCD":"WAF150051VBE0000"}},
{"type":"Feature","geometry":{"type":"Point","coordinates":[120.281388,50.246442]},"properties":{"ADCD":"150784400505000","PID":"1507844005050000f00M","NAME":"平原屯（第七生产队）安置点","ADDRESS":"村北","LGTD":120.281388,"LTTD":50.246442,"REMARK":"位于村落北侧，地势较高、平坦开阔，地质条件良好，能够容纳转移人口\r\n","dateStr":"2018-06-11 03:50:53","isPlot":1,"crtDate":"2018-06-08T00:00:00.000Z","crtUser":"admin","picPath":"","status":1,"cDefine1":"","POPULATION":11,"DBVER":"0f20180611035053368","RECORDMAN":"管理员(admin)#&#010-68781602","ZPID":"1507844005050000f00E01","WSCD":"WAF150021QB00000"}},
{"type":"Feature","geometry":{"type":"Point","coordinates":[119.3524206,50.1255896]},"properties":{"ADCD":"150784101200101","PID":"1506271022080000f00N","NAME":"安置点","ADDRESS":"","LGTD":119.352421,"LTTD":50.12559,"REMARK":"\r\n","dateStr":"2018-06-08 01:35:14","isPlot":1,"crtDate":"2018-06-08T00:00:00.000Z","crtUser":"admin","picPath":"","status":0,"cDefine1":"","POPULATION":0,"DBVER":"0f20180608013521974","RECORDMAN":"管理员(admin)#&#010-68781602","ZPID":"","WSCD":"WAF1B00700000000"}},
{"type":"Feature","geometry":{"type":"Point","coordinates":[119.546849,50.214307]},"properties":{"ADCD":"150784101200101","PID":"1506271022080000f00O","NAME":"梁东村村委会安置点","ADDRESS":"村西","LGTD":119.546849,"LTTD":50.214307,"REMARK":"位于村落西侧，地势较高、平坦开阔，地质条件良好，能够容纳转移人口\r\n","dateStr":"2018-06-11 03:02:23","isPlot":1,"crtDate":"2018-06-08T00:00:00.000Z","crtUser":"admin","picPath":"","status":1,"cDefine1":"","POPULATION":52,"DBVER":"0f20180611030223152","RECORDMAN":"管理员(admin)#&#010-68781602","ZPID":"1506271022080000f00F02","WSCD":"WAF1B00700000000"}},
{"type":"Feature","geometry":{"type":"Point","coordinates":[120.791974,51.266268]},"properties":{"ADCD":"150784103013000","PID":"1507841030130000f00P","NAME":"龙岩社区安置点1","ADDRESS":"村东","LGTD":120.791974,"LTTD":51.266268,"REMARK":"位于村落东侧，地势较高、平坦开阔，地质条件良好，能够容纳转移人口\r\n","dateStr":"2018-06-11 04:05:13","isPlot":1,"crtDate":"2018-06-08T00:00:00.000Z","crtUser":"admin","picPath":"","status":1,"cDefine1":"","POPULATION":156,"DBVER":"0f20180611040512627","RECORDMAN":"管理员(admin)#&#010-68781602","ZPID":"1507841030130000f00H01","WSCD":"WAF1700700000000"}},
{"type":"Feature","geometry":{"type":"Point","coordinates":[119.7634,51.106542]},"properties":{"ADCD":"150784211501101","PID":"1507842115011010f00Q","NAME":"水磨生产队安置点","ADDRESS":"村东","LGTD":119.7634,"LTTD":51.106542,"REMARK":"位于村落东侧，地势较高、平坦开阔，地质条件良好，能够容纳转移人口\r\n","dateStr":"2018-06-11 04:00:00","isPlot":1,"crtDate":"2018-06-08T00:00:00.000Z","crtUser":"admin","picPath":"","status":1,"cDefine1":"","POPULATION":42,"DBVER":"0f20180611040000358","RECORDMAN":"管理员(admin)#&#010-68781602","ZPID":"1507842115011010f00I01","WSCD":"WAF0000004BAA000"}},
{"type":"Feature","geometry":{"type":"Point","coordinates":[120.317385,51.357853]},"properties":{"ADCD":"150784103400102","PID":"1507841034001020f00R","NAME":"长青林场安置点","ADDRESS":"村东","LGTD":120.317385,"LTTD":51.357853,"REMARK":"位于村落东侧，地势较高、平坦开阔，地质条件良好，能够容纳转移人口\r\n","dateStr":"2018-06-11 04:13:22","isPlot":1,"crtDate":"2018-06-08T00:00:00.000Z","crtUser":"admin","picPath":"","status":1,"cDefine1":"","POPULATION":10,"DBVER":"0f20180611041321918","RECORDMAN":"管理员(admin)#&#010-68781602","ZPID":"1507841034001020f00J01","WSCD":"WAF1710A00000000"}},
{"type":"Feature","geometry":{"type":"Point","coordinates":[119.536153,50.261944]},"properties":{"ADCD":"150784401503000","PID":"1507844015030000f00S","NAME":"奶牛村（第九生产队）安置点","ADDRESS":"村北","LGTD":119.536153,"LTTD":50.261944,"REMARK":"位于村落北侧，地势较高、平坦开阔，地质条件良好，能够容纳转移人口\r\n","dateStr":"2018-06-11 05:10:45","isPlot":1,"crtDate":"2018-06-08T00:00:00.000Z","crtUser":"admin","picPath":"","status":1,"cDefine1":"","POPULATION":42,"DBVER":"0f20180611051045067","RECORDMAN":"管理员(admin)#&#010-68781602","ZPID":"1507844015030000f00K01","WSCD":"WAF16001y0000000"}},
{"type":"Feature","geometry":{"type":"Point","coordinates":[120.744905,51.266393]},"properties":{"ADCD":"150784103015000","PID":"1507841030150000f00T","NAME":"圃园社区安置点","ADDRESS":"村东","LGTD":120.744905,"LTTD":51.266393,"REMARK":"位于村落东侧，地势较高、平坦开阔，地质条件良好，能够容纳转移人口\r\n","dateStr":"2018-06-11 04:14:40","isPlot":1,"crtDate":"2018-06-08T00:00:00.000Z","crtUser":"admin","picPath":"","status":1,"cDefine1":"","POPULATION":24,"DBVER":"0f20180611041439902","RECORDMAN":"管理员(admin)#&#010-68781602","ZPID":"1507841030150000f00L01","WSCD":"WAF1700700000000"}},
{"type":"Feature","geometry":{"type":"Point","coordinates":[120.76508,52.186815]},"properties":{"ADCD":"150784212201000","PID":"1507842122010000f00U","NAME":"奇乾村安置点","ADDRESS":"村南","LGTD":120.76508,"LTTD":52.186815,"REMARK":"位于村落南侧，地势较高、平坦开阔，地质条件良好，能够容纳转移人口\r\n","dateStr":"2018-06-11 04:18:00","isPlot":1,"crtDate":"2018-06-08T00:00:00.000Z","crtUser":"admin","picPath":"","status":1,"cDefine1":"","POPULATION":10,"DBVER":"0f20180611041759579","RECORDMAN":"管理员(admin)#&#010-68781602","ZPID":"1507842122010000f00M01","WSCD":"WAF1900Q00000000"}},
{"type":"Feature","geometry":{"type":"Point","coordinates":[120.437634,50.247882]},"properties":{"ADCD":"150784002201100","PID":"1507840022010000f00V","NAME":"前进村村委会安置点","ADDRESS":"村西","LGTD":120.437634,"LTTD":50.247882,"REMARK":"位于村落西侧，地势较高、平坦开阔，地质条件良好，能够容纳转移人口\r\n","dateStr":"2018-06-11 12:30:53","isPlot":1,"crtDate":"2018-06-08T00:00:00.000Z","crtUser":"admin","picPath":"","status":1,"cDefine1":"","POPULATION":42,"DBVER":"0f20180611123053166","RECORDMAN":"管理员(admin)#&#010-68781602","ZPID":"1507840022010000f00N","WSCD":"WAF1550700000000"}},
{"type":"Feature","geometry":{"type":"Point","coordinates":[120.784357,50.277551]},"properties":{"ADCD":"150784002201101","PID":"1507840022011010f00W","NAME":"前进村作业点安置点","ADDRESS":"村东","LGTD":120.784357,"LTTD":50.277551,"REMARK":"位于村落东侧，地势较高、平坦开阔，地质条件良好，能够容纳转移人口\r\n","dateStr":"2018-06-11 12:32:12","isPlot":1,"crtDate":"2018-06-08T00:00:00.000Z","crtUser":"admin","picPath":"","status":1,"cDefine1":"","POPULATION":12,"DBVER":"0f20180611123211457","RECORDMAN":"管理员(admin)#&#010-68781602","ZPID":"1507840022011010f00O","WSCD":"WAF150011GBD0000"}},
{"type":"Feature","geometry":{"type":"Point","coordinates":[120.435597,50.216366]},"properties":{"ADCD":"150784402502000","PID":"1507844025020000f00X","NAME":"青年沟屯（第五生产队）安置点","ADDRESS":"西北侧","LGTD":120.435597,"LTTD":50.216366,"REMARK":"位于村落西北侧，地势较高、平坦开阔，地质条件良好，能够容纳转移人口\r\n","dateStr":"2018-06-11 12:37:41","isPlot":1,"crtDate":"2018-06-08T00:00:00.000Z","crtUser":"admin","picPath":"","status":1,"cDefine1":"","POPULATION":36,"DBVER":"0f20180611123741109","RECORDMAN":"管理员(admin)#&#010-68781602","ZPID":"1507844025020000f00P","WSCD":"WAF15501EE000000"}},
{"type":"Feature","geometry":{"type":"Point","coordinates":[120.100222,50.449438]},"properties":{"ADCD":"150784200006000","PID":"1507842000030000f00Y","NAME":"第二社区居委会安置点","ADDRESS":"村北","LGTD":120.100222,"LTTD":50.449438,"REMARK":"位于村落北侧，地势较高、平坦开阔，地质条件良好，能够容纳转移人口\r\n","dateStr":"2018-06-11 04:19:23","isPlot":1,"crtDate":"2018-06-08T00:00:00.000Z","crtUser":"admin","picPath":"","status":1,"cDefine1":"","POPULATION":12,"DBVER":"0f20180611041923541","RECORDMAN":"管理员(admin)#&#010-68781602","ZPID":"1507842000030000f00Q01","WSCD":"WAF16301IA000000"}},
{"type":"Feature","geometry":{"type":"Point","coordinates":[119.720471,50.362698]},"properties":{"ADCD":"150784401506000","PID":"1507844015060000f00Z","NAME":"得尔布屯（第十一生产队）安置点","ADDRESS":"村南","LGTD":119.720471,"LTTD":50.362698,"REMARK":"位于村落南侧，地势较高、平坦开阔，地质条件良好，能够容纳转移人口\r\n","dateStr":"2018-06-11 04:44:21","isPlot":1,"crtDate":"2018-06-08T00:00:00.000Z","crtUser":"admin","picPath":"","status":1,"cDefine1":"","POPULATION":14,"DBVER":"0f20180611044421021","RECORDMAN":"管理员(admin)#&#010-68781602","ZPID":"1507844015060000f00R01","WSCD":"WAF1600m00000000"}},
{"type":"Feature","geometry":{"type":"Point","coordinates":[120.041013,50.272638]},"properties":{"ADCD":"150784401502000","PID":"1507844015020000f010","NAME":"好尔基屯（第七生产队）安置点","ADDRESS":"村南","LGTD":120.041013,"LTTD":50.272638,"REMARK":"位于村落南侧，地势较高、平坦开阔，地质条件良好，能够容纳转移人口\r\n","dateStr":"2018-06-11 05:10:11","isPlot":1,"crtDate":"2018-06-08T00:00:00.000Z","crtUser":"admin","picPath":"","status":1,"cDefine1":"","POPULATION":15,"DBVER":"0f20180611051011251","RECORDMAN":"管理员(admin)#&#010-68781602","ZPID":"1507844015020000f00S01","WSCD":"WAF150011TBA0000"}},
{"type":"Feature","geometry":{"type":"Point","coordinates":[119.971876,50.23415]},"properties":{"ADCD":"150784401505000","PID":"1507844015050000f011","NAME":"其洛图屯（第十生产队）安置点","ADDRESS":"村西","LGTD":119.971876,"LTTD":50.23415,"REMARK":"位于村落西侧，地势较高、平坦开阔，地质条件良好，能够容纳转移人口\r\n","dateStr":"2018-06-11 05:13:16","isPlot":1,"crtDate":"2018-06-08T00:00:00.000Z","crtUser":"admin","picPath":"","status":1,"cDefine1":"","POPULATION":24,"DBVER":"0f20180611051315928","RECORDMAN":"管理员(admin)#&#010-68781602","ZPID":"1507844015050000f00T01","WSCD":"WAF150031UB00000"}},
{"type":"Feature","geometry":{"type":"Point","coordinates":[119.678861,50.257786]},"properties":{"ADCD":"150784401507000","PID":"1507844015070000f012","NAME":"西地营子屯（第十二生产队）危安置点","ADDRESS":"村北","LGTD":119.678861,"LTTD":50.257786,"REMARK":"位于村落北侧，地势较高、平坦开阔，地质条件良好，能够容纳转移人口\r\n","dateStr":"2018-06-11 12:00:02","isPlot":1,"crtDate":"2018-06-08T00:00:00.000Z","crtUser":"admin","picPath":"","status":1,"cDefine1":"","POPULATION":18,"DBVER":"0f20180611120001649","RECORDMAN":"管理员(admin)#&#010-68781602","ZPID":"1507844015070000f00U","WSCD":"WAF150061dB00000"}},
{"type":"Feature","geometry":{"type":"Point","coordinates":[120.452825,50.267108]},"properties":{"ADCD":"150784002101101","PID":"1507840021010000f013","NAME":"第三生产队安置点","ADDRESS":"村东","LGTD":120.452825,"LTTD":50.267108,"REMARK":"位于村落东侧，地势较高、平坦开阔，地质条件良好，能够容纳转移人口\r\n","dateStr":"2018-06-11 12:08:41","isPlot":1,"crtDate":"2018-06-08T00:00:00.000Z","crtUser":"admin","picPath":"","status":1,"cDefine1":"","POPULATION":45,"DBVER":"0f20180611120840747","RECORDMAN":"管理员(admin)#&#010-68781602","ZPID":"1507840021010000f01d","WSCD":"WAF1550700000000"}},
{"type":"Feature","geometry":{"type":"Point","coordinates":[120.46895,50.250958]},"properties":{"ADCD":"150784002101102","PID":"1507840021010000f014","NAME":"第四生产队安置点","ADDRESS":"村东","LGTD":120.46895,"LTTD":50.250958,"REMARK":"位于村落东侧，地势较高、平坦开阔，地质条件良好，能够容纳转移人口\r\n","dateStr":"2018-06-12 02:52:15","isPlot":1,"crtDate":"2018-06-08T00:00:00.000Z","crtUser":"admin","picPath":"","status":1,"cDefine1":"","POPULATION":339,"DBVER":"0f20180612025215325","RECORDMAN":"管理员(admin)#&#010-68781602","ZPID":"1507840022010000f00d","WSCD":"WAF1550700000000"}},
{"type":"Feature","geometry":{"type":"Point","coordinates":[120.100728,50.449561]},"properties":{"ADCD":"150784200003000","PID":"1507842000030000f015","NAME":"苏沁居委会安置点","ADDRESS":"村西","LGTD":120.100728,"LTTD":50.449561,"REMARK":"位于村落西侧，地势较高、平坦开阔，地质条件良好，能够容纳转移人口\r\n","dateStr":"2018-06-11 04:35:02","isPlot":1,"crtDate":"2018-06-08T00:00:00.000Z","crtUser":"admin","picPath":"","status":1,"cDefine1":"","POPULATION":56,"DBVER":"0f20180611043501879","RECORDMAN":"管理员(admin)#&#010-68781602","ZPID":"1507842000030000f00V01","WSCD":"WAF16301I0000000"}},
{"type":"Feature","geometry":{"type":"Point","coordinates":[120.025448,50.579566]},"properties":{"ADCD":"150784403502000","PID":"1507844035020000f016","NAME":"团结屯安置点","ADDRESS":"村北","LGTD":120.025448,"LTTD":50.579566,"REMARK":"位于村落北侧，地势较高、平坦开阔，地质条件良好，能够容纳转移人口\r\n","dateStr":"2018-06-13 18:21:13","isPlot":1,"crtDate":"2018-06-08T00:00:00.000Z","crtUser":"admin","picPath":"","status":1,"cDefine1":"","POPULATION":33,"DBVER":"2o20180613182113427","RECORDMAN":"管理员(admin)#&#010-68781602","ZPID":"1507844035020000f00X","WSCD":"WAF1600a00000000"}},
{"type":"Feature","geometry":{"type":"Point","coordinates":[119.6433802931,50.5560773969]},"properties":{"ADCD":"150784403503000","PID":"1507844035030000f017","NAME":"安置点","ADDRESS":"","LGTD":119.64338,"LTTD":50.556077,"REMARK":"\r\n","dateStr":"2018-06-08 09:38:52","isPlot":1,"crtDate":"2018-06-08T00:00:00.000Z","crtUser":"admin","picPath":"","status":0,"cDefine1":"","POPULATION":0,"DBVER":"0f20180608093933793","RECORDMAN":"管理员(admin)#&#010-68781602","ZPID":"","WSCD":"WAF1610a00000000"}},
{"type":"Feature","geometry":{"type":"Point","coordinates":[119.650868,50.541341]},"properties":{"ADCD":"150784403503000","PID":"1507844035030000f018","NAME":"永胜屯安置点","ADDRESS":"村西北","LGTD":119.650868,"LTTD":50.541341,"REMARK":"位于村落西北侧，地势较高、平坦开阔，地质条件良好，能够容纳转移人口\r\n","dateStr":"2018-06-11 13:22:46","isPlot":1,"crtDate":"2018-06-08T00:00:00.000Z","crtUser":"admin","picPath":"","status":1,"cDefine1":"","POPULATION":62,"DBVER":"0f20180611132245963","RECORDMAN":"管理员(admin)#&#010-68781602","ZPID":"1507844035030000f00Y","WSCD":"WAF1610a00000000"}},
{"type":"Feature","geometry":{"type":"Point","coordinates":[120.804871,50.368586]},"properties":{"ADCD":"150784402507000","PID":"1507844025070000f019","NAME":"伊根队安置点","ADDRESS":"村北","LGTD":120.804871,"LTTD":50.368586,"REMARK":"位于村落北侧，地势较高、平坦开阔，地质条件良好，能够容纳转移人口\r\n","dateStr":"2018-06-11 13:02:20","isPlot":1,"crtDate":"2018-06-08T00:00:00.000Z","crtUser":"admin","picPath":"","status":1,"cDefine1":"","POPULATION":85,"DBVER":"0f20180611130219838","RECORDMAN":"管理员(admin)#&#010-68781602","ZPID":"1507844025070000f00Z","WSCD":"WAF1520J00000000"}},
{"type":"Feature","geometry":{"type":"Point","coordinates":[120.661898,50.231717]},"properties":{"ADCD":"150784402500000","PID":"1507844025000000f01a","NAME":"新库力屯（第一生产队）安置点1","ADDRESS":"村南","LGTD":120.661898,"LTTD":50.231717,"REMARK":"位于村落南侧，地势较高、平坦开阔，地质条件良好，能够容纳转移人口\r\n","dateStr":"2018-06-13 15:24:26","isPlot":1,"crtDate":"2018-06-08T00:00:00.000Z","crtUser":"admin","picPath":"","status":1,"cDefine1":"","POPULATION":54,"DBVER":"2o20180613152426143","RECORDMAN":"管理员(admin)#&#010-68781602","ZPID":"1507844025000000f010","WSCD":"WAF15501CA000000"}},
{"type":"Feature","geometry":{"type":"Point","coordinates":[120.661414,50.237866]},"properties":{"ADCD":"150784402500000","PID":"1507844025000000f01b","NAME":"新库力屯（第一生产队）安置点2","ADDRESS":"村东北","LGTD":120.661414,"LTTD":50.237866,"REMARK":"位于村落东北侧，地势较高、平坦开阔，地质条件良好，能够容纳转移人口\r\n","dateStr":"2018-06-11 13:00:54","isPlot":1,"crtDate":"2018-06-08T00:00:00.000Z","crtUser":"admin","picPath":"","status":1,"cDefine1":"","POPULATION":36,"DBVER":"0f20180611130053856","RECORDMAN":"管理员(admin)#&#010-68781602","ZPID":"1507844025000000f011","WSCD":"WAF15501CA000000"}},
{"type":"Feature","geometry":{"type":"Point","coordinates":[120.352545,50.246386]},"properties":{"ADCD":"150784402506000","PID":"1507844025060000f01c","NAME":"育良屯（第六生产队）安置点","ADDRESS":"村南","LGTD":120.352545,"LTTD":50.246386,"REMARK":"位于村落南侧，地势较高、平坦开阔，地质条件良好，能够容纳转移人口\r\n","dateStr":"2018-06-11 13:03:10","isPlot":1,"crtDate":"2018-06-08T00:00:00.000Z","crtUser":"admin","picPath":"","status":1,"cDefine1":"","POPULATION":62,"DBVER":"0f20180611130310236","RECORDMAN":"管理员(admin)#&#010-68781602","ZPID":"1507844025060000f012","WSCD":"WAF15501F0000000"}},
{"type":"Feature","geometry":{"type":"Point","coordinates":[120.796595,51.252284]},"properties":{"ADCD":"150784103011000","PID":"1507841030110000f01d","NAME":"兴安社区安置点","ADDRESS":"村东","LGTD":120.796595,"LTTD":51.252284,"REMARK":"位于村落东侧，地势较高、平坦开阔，地质条件良好，能够容纳转移人口\r\n","dateStr":"2018-06-11 04:15:12","isPlot":1,"crtDate":"2018-06-08T00:00:00.000Z","crtUser":"admin","picPath":"","status":1,"cDefine1":"","POPULATION":29,"DBVER":"0f20180611041511613","RECORDMAN":"管理员(admin)#&#010-68781602","ZPID":"1507841030120000f01301","WSCD":"WAF1700500000000"}},
{"type":"Feature","geometry":{"type":"Point","coordinates":[120.786642,51.242287]},"properties":{"ADCD":"150784103012000","PID":"1507841030120000f01e","NAME":"兴林社区安置点","ADDRESS":"村南","LGTD":120.786642,"LTTD":51.242287,"REMARK":"位于村落南侧，地势较高、平坦开阔，地质条件良好，能够容纳转移人口\r\n","dateStr":"2018-06-11 04:17:19","isPlot":1,"crtDate":"2018-06-08T00:00:00.000Z","crtUser":"admin","picPath":"","status":1,"cDefine1":"","POPULATION":25,"DBVER":"0f20180611041718576","RECORDMAN":"管理员(admin)#&#010-68781602","ZPID":"1507841030120000f01401","WSCD":"WAF1700500000000"}},
{"type":"Feature","geometry":{"type":"Point","coordinates":[119.949103,50.17623]},"properties":{"ADCD":"150784400503000","PID":"1507844005030000f01f","NAME":"振兴屯（第四生产队）安置点","ADDRESS":"村南","LGTD":119.949103,"LTTD":50.17623,"REMARK":"位于村落南侧，地势较高、平坦开阔，地质条件良好，能够容纳转移人口\r\n","dateStr":"2018-06-11 03:55:23","isPlot":1,"crtDate":"2018-06-08T00:00:00.000Z","crtUser":"admin","picPath":"","status":1,"cDefine1":"","POPULATION":72,"DBVER":"0f20180611035522861","RECORDMAN":"管理员(admin)#&#010-68781602","ZPID":"1507844005030000f01501","WSCD":"WAF150041WB00000"}},
{"type":"Feature","geometry":{"type":"Point","coordinates":[119.96215978366764,50.18175092851806]},"properties":{"ADCD":"150784400503000","PID":"1507844005030000f01g","NAME":"安置点2","ADDRESS":"村南","LGTD":119.96216,"LTTD":50.181751,"REMARK":"位于村落南侧，地势较高、平坦开阔，地质条件良好，能够容纳转移人口\r\n","dateStr":"2018-06-11 03:53:56","isPlot":1,"crtDate":"2018-06-08T00:00:00.000Z","crtUser":"admin","picPath":"","status":0,"cDefine1":"","POPULATION":28,"DBVER":"0f20180611035401568","RECORDMAN":"管理员(admin)#&#010-68781602","ZPID":"","WSCD":"WAF150041WB00000"}},
{"type":"Feature","geometry":{"type":"Point","coordinates":[119.827528,50.176213]},"properties":{"ADCD":"150784400504000","PID":"1507844005040000f01h","NAME":"睦邻屯（第六生产队）安置点","ADDRESS":"村东南","LGTD":119.827528,"LTTD":50.176213,"REMARK":"位于村落东南侧，地势较高、平坦开阔，地质条件良好，能够容纳转移人口\r\n","dateStr":"2018-06-11 03:43:54","isPlot":1,"crtDate":"2018-06-08T00:00:00.000Z","crtUser":"admin","picPath":"","status":1,"cDefine1":"","POPULATION":16,"DBVER":"0f20180611034353879","RECORDMAN":"管理员(admin)#&#010-68781602","ZPID":"1507844005040000f01701","WSCD":""}},
{"type":"Feature","geometry":{"type":"Point","coordinates":[120.51054,50.382368]},"properties":{"ADCD":"150784402505000","PID":"1507844025050000f01i","NAME":"小乌尔根屯（第八生产队）安置点","ADDRESS":"村北","LGTD":120.51054,"LTTD":50.382368,"REMARK":"位于村落北侧，地势较高、平坦开阔，地质条件良好，能够容纳转移人口\r\n","dateStr":"2018-06-12 04:00:52","isPlot":1,"crtDate":"2018-06-08T00:00:00.000Z","crtUser":"admin","picPath":"","status":1,"cDefine1":"","POPULATION":134,"DBVER":"0f20180612040052010","RECORDMAN":"管理员(admin)#&#010-68781602","ZPID":"1507844025050000f018","WSCD":"WAF150061EB00000"}},
{"type":"Feature","geometry":{"type":"Point","coordinates":[119.906762,51.328928]},"properties":{"ADCD":"150784211001000","PID":"1507842110010000f01j","NAME":"天骄社区危安置点","ADDRESS":"村南","LGTD":119.906762,"LTTD":51.328928,"REMARK":"位于村落南侧，地势较高、平坦开阔，地质条件良好，能够容纳转移人口\r\n","dateStr":"2018-06-11 04:01:52","isPlot":1,"crtDate":"2018-06-08T00:00:00.000Z","crtUser":"admin","picPath":"","status":1,"cDefine1":"","POPULATION":12,"DBVER":"0f20180611040151630","RECORDMAN":"管理员(admin)#&#010-68781602","ZPID":"1507842110010000f00a01","WSCD":"WAF3T00A00000000"}},
{"type":"Feature","geometry":{"type":"Point","coordinates":[120.0986853303,50.4631345061]},"properties":{"ADCD":"150784403506000","PID":"1507844035060000f01k","NAME":"安置点","ADDRESS":"","LGTD":120.098685,"LTTD":50.463135,"REMARK":"\r\n","dateStr":"2018-06-08 14:10:30","isPlot":1,"crtDate":"2018-06-08T00:00:00.000Z","crtUser":"admin","picPath":"","status":0,"cDefine1":"","POPULATION":0,"DBVER":"0f20180612042132762","RECORDMAN":"管理员(admin)#&#010-68781602","ZPID":"","WSCD":"WAF16002n0000000"}},
{"type":"Feature","geometry":{"type":"Point","coordinates":[120.098685,50.463135]},"properties":{"ADCD":"150784200005000","PID":"1507844035060000f01l","NAME":"第一社区居委会安置点1","ADDRESS":"村北","LGTD":120.098685,"LTTD":50.463135,"REMARK":"位于村落东侧，地势较高、平坦开阔，地质条件良好，能够容纳转移人口\r\n","dateStr":"2018-06-13 14:39:08","isPlot":1,"crtDate":"2018-06-08T00:00:00.000Z","crtUser":"admin","picPath":"","status":1,"cDefine1":"","POPULATION":70,"DBVER":"2o20180613143907860","RECORDMAN":"管理员(admin)#&#010-68781602","ZPID":"1507842000050000f00h01","WSCD":"WAF16002p0000000"}},
{"type":"Feature","geometry":{"type":"Point","coordinates":[119.756152,50.458565]},"properties":{"ADCD":"150784403506000","PID":"1507844035060000f01m","NAME":"苏沁牧场安置点1","ADDRESS":"村西","LGTD":119.756152,"LTTD":50.458565,"REMARK":"位于村落西侧，地势较高、平坦开阔，地质条件良好，能够容纳转移人口\r\n","dateStr":"2018-06-13 18:20:00","isPlot":1,"crtDate":"2018-06-08T00:00:00.000Z","crtUser":"admin","picPath":"","status":1,"cDefine1":"","POPULATION":194,"DBVER":"2o20180613182000251","RECORDMAN":"管理员(admin)#&#010-68781602","ZPID":"1507844035060000f00b01","WSCD":"WAF16002n0000000"}},
{"type":"Feature","geometry":{"type":"Point","coordinates":[119.563585,50.489872]},"properties":{"ADCD":"150784403505000","PID":"1507844035050000f01n","NAME":"泉山子屯安置点","ADDRESS":"村北","LGTD":119.563585,"LTTD":50.489872,"REMARK":"位于村落东侧，地势较高、平坦开阔，地质条件良好，能够容纳转移人口\r\n","dateStr":"2018-06-11 13:11:00","isPlot":1,"crtDate":"2018-06-08T00:00:00.000Z","crtUser":"admin","picPath":"","status":1,"cDefine1":"","POPULATION":35,"DBVER":"0f20180611131059957","RECORDMAN":"管理员(admin)#&#010-68781602","ZPID":"1507844035050000f019","WSCD":"WAF1610d00000000"}},
{"type":"Feature","geometry":{"type":"Point","coordinates":[120.091785,50.459271]},"properties":{"ADCD":"150784401509000","PID":"1507842000050000f01o","NAME":"第三生产队安置点2","ADDRESS":"村西","LGTD":120.091785,"LTTD":50.459271,"REMARK":"位于村落西侧，地势较高、平坦开阔，地质条件良好，能够容纳转移人口\r\n","dateStr":"2018-06-12 03:52:41","isPlot":1,"crtDate":"2018-06-08T00:00:00.000Z","crtUser":"admin","picPath":"","status":1,"cDefine1":"","POPULATION":127,"DBVER":"0f20180612035240713","RECORDMAN":"管理员(admin)#&#010-68781602","ZPID":"1507842000060000f00f02","WSCD":"WAF16301IA000000"}},
{"type":"Feature","geometry":{"type":"Point","coordinates":[120.24451,50.668456]},"properties":{"ADCD":"150784401501000","PID":"1507844015010000f01p","NAME":"上护林屯六队安置点1","ADDRESS":"村南","LGTD":120.24451,"LTTD":50.668456,"REMARK":"位于村落南侧，地势较高、平坦开阔，地质条件良好，能够容纳转移人口\r\n","dateStr":"2018-06-13 17:55:19","isPlot":1,"crtDate":"2018-06-08T00:00:00.000Z","crtUser":"admin","picPath":"","status":1,"cDefine1":"","POPULATION":110,"DBVER":"2o20180613175518891","RECORDMAN":"管理员(admin)#&#010-68781602","ZPID":"1507844015010000f01h","WSCD":"WAF1600S00000000"}},
{"type":"Feature","geometry":{"type":"Point","coordinates":[120.177097,50.633757]},"properties":{"ADCD":"150784401500000","PID":"1507844015000000f01q","NAME":"下护林屯（五队）安置点","ADDRESS":"村南","LGTD":120.177097,"LTTD":50.633757,"REMARK":"位于村落南侧，地势较高、平坦开阔，地质条件良好，能够容纳转移人口\r\n","dateStr":"2018-06-12 03:39:23","isPlot":1,"crtDate":"2018-06-08T00:00:00.000Z","crtUser":"admin","picPath":"","status":1,"cDefine1":"","POPULATION":68,"DBVER":"0f20180612033922411","RECORDMAN":"管理员(admin)#&#010-68781602","ZPID":"1507844015000000f01b","WSCD":"WAF16001a0000000"}},
{"type":"Feature","geometry":{"type":"Point","coordinates":[120.086393,50.483667]},"properties":{"ADCD":"150784401508000","PID":"1507844015080000f01r","NAME":"第一生产队安置点","ADDRESS":"村东","LGTD":120.086393,"LTTD":50.483667,"REMARK":"位于村落东侧，地势较高、平坦开阔，地质条件良好，能够容纳转移人口\r\n","dateStr":"2018-06-12 03:47:52","isPlot":1,"crtDate":"2018-06-08T00:00:00.000Z","crtUser":"admin","picPath":"","status":1,"cDefine1":"","POPULATION":46,"DBVER":"0f20180612034751928","RECORDMAN":"管理员(admin)#&#010-68781602","ZPID":"1507844015080000f01c01","WSCD":"WAF1630900000000"}},
{"type":"Feature","geometry":{"type":"Point","coordinates":[120.19439314739206,50.09758674820409]},"properties":{"ADCD":"150784400508000","PID":"1507844005080000f01s","NAME":"安置点2","ADDRESS":"","LGTD":120.194393,"LTTD":50.097587,"REMARK":"\r\n","dateStr":"2018-06-08 21:31:09","isPlot":1,"crtDate":"2018-06-08T00:00:00.000Z","crtUser":"admin","picPath":"","status":0,"cDefine1":"","POPULATION":0,"DBVER":"0f20180608213118077","RECORDMAN":"管理员(admin)#&#010-68781602","ZPID":"","WSCD":"WAF150041VB00000"}},
{"type":"Feature","geometry":{"type":"Point","coordinates":[120.768091,51.271121]},"properties":{"ADCD":"150784103013000","PID":"1507841030130000f01t","NAME":"龙岩社区安置点2","ADDRESS":"村西","LGTD":120.768091,"LTTD":51.271121,"REMARK":"位于村落西侧，地势较高、平坦开阔，地质条件良好，能够容纳转移人口\r\n","dateStr":"2018-06-11 04:04:20","isPlot":1,"crtDate":"2018-06-08T00:00:00.000Z","crtUser":"admin","picPath":"","status":1,"cDefine1":"","POPULATION":346,"DBVER":"0f20180611040419924","RECORDMAN":"管理员(admin)#&#010-68781602","ZPID":"1507841030130000f00G01","WSCD":"WAF1700700000000"}},
{"type":"Feature","geometry":{"type":"Point","coordinates":[120.47077522128748,50.251579670941574]},"properties":{"ADCD":"150784002101000","PID":"1507840021010000f01u","NAME":"安置点","ADDRESS":"","LGTD":120.470775,"LTTD":50.25158,"REMARK":"\r\n","dateStr":"2018-06-08 22:23:54","isPlot":1,"crtDate":"2018-06-08T00:00:00.000Z","crtUser":"admin","picPath":"","status":0,"cDefine1":"","POPULATION":0,"DBVER":"0f20180608222428170","RECORDMAN":"管理员(admin)#&#010-68781602","ZPID":"","WSCD":"WAF1550700000000"}},
{"type":"Feature","geometry":{"type":"Point","coordinates":[120.440666,50.267991]},"properties":{"ADCD":"150784002101100","PID":"1507840021010000f01v","NAME":"共建社区居委会安置点","ADDRESS":"村北","LGTD":120.440666,"LTTD":50.267991,"REMARK":"位于村落北侧，地势较高、平坦开阔，地质条件良好，能够容纳转移人口\r\n","dateStr":"2018-06-11 12:29:48","isPlot":1,"crtDate":"2018-06-08T00:00:00.000Z","crtUser":"admin","picPath":"","status":1,"cDefine1":"","POPULATION":59,"DBVER":"0f20180611122948441","RECORDMAN":"管理员(admin)#&#010-68781602","ZPID":"1507840021010000f01e","WSCD":"WAF1550700000000"}},
{"type":"Feature","geometry":{"type":"Point","coordinates":[119.842974,50.248948]},"properties":{"ADCD":"150784401504000","PID":"1507844015040000f01w","NAME":"北山屯（第八生产队）安置点","ADDRESS":"村东","LGTD":119.842974,"LTTD":50.248948,"REMARK":"位于村落东侧，地势较高、平坦开阔，地质条件良好，能够容纳转移人口\r\n","dateStr":"2018-06-12 03:45:39","isPlot":1,"crtDate":"2018-06-09T00:00:00.000Z","crtUser":"admin","picPath":"","status":1,"cDefine1":"","POPULATION":247,"DBVER":"0f20180612034538570","RECORDMAN":"管理员(admin)#&#010-68781602","ZPID":"1507844015040000f01f01","WSCD":"WAF150011dBA0000"}},
{"type":"Feature","geometry":{"type":"Point","coordinates":[119.519727,50.750341]},"properties":{"ADCD":"150784210500103","PID":"1507842105001030f01x","NAME":"七卡生产队安置点1","ADDRESS":"村北","LGTD":119.519727,"LTTD":50.750341,"REMARK":"位于村落北侧，地势较高、平坦开阔，地质条件良好，能够容纳转移人口\r\n","dateStr":"2018-06-12 03:14:27","isPlot":1,"crtDate":"2018-06-11T00:00:00.000Z","crtUser":"admin","picPath":"","status":1,"cDefine1":"","POPULATION":91,"DBVER":"0f20180612031427271","RECORDMAN":"管理员(admin)#&#010-68781602","ZPID":"1507842105001030f01k01","WSCD":"WAF1K00600000000"}},
{"type":"Feature","geometry":{"type":"Point","coordinates":[119.568035,50.365077]},"properties":{"ADCD":"150784403504000","PID":"1507844035040000f01y","NAME":"红旗屯安置点1","ADDRESS":"村北","LGTD":119.568035,"LTTD":50.365077,"REMARK":"位于村落北侧，地势较高、平坦开阔，地质条件良好，能够容纳转移人口\r\n","dateStr":"2018-06-13 15:31:23","isPlot":1,"crtDate":"2018-06-11T00:00:00.000Z","crtUser":"admin","picPath":"","status":1,"cDefine1":"","POPULATION":129,"DBVER":"2o20180613153122983","RECORDMAN":"管理员(admin)#&#010-68781602","ZPID":"1507844035040000f01l01","WSCD":"WAF16002v0000000"}},
{"type":"Feature","geometry":{"type":"Point","coordinates":[120.275041,50.024831]},"properties":{"ADCD":"150784400511000","PID":"1507844005110000f01z","NAME":"良种站村（第五生产队）安置点2","ADDRESS":"村西","LGTD":120.275041,"LTTD":50.024831,"REMARK":"位于村落西侧，地势较高、平坦开阔，地质条件良好，能够容纳转移人口\r\n","dateStr":"2018-06-12 03:36:55","isPlot":1,"crtDate":"2018-06-11T00:00:00.000Z","crtUser":"admin","picPath":"","status":1,"cDefine1":"","POPULATION":8,"DBVER":"0f20180612033655041","RECORDMAN":"管理员(admin)#&#010-68781602","ZPID":"1507844005110000f01n","WSCD":"WAF150011VB00000"}},
{"type":"Feature","geometry":{"type":"Point","coordinates":[120.181313,50.06633]},"properties":{"ADCD":"150784400507000","PID":"1507844005070000f01A","NAME":"南山屯（一0五生产队）安置点2","ADDRESS":"村东","LGTD":120.181313,"LTTD":50.06633,"REMARK":"位于村落东侧，地势较高、平坦开阔，地质条件良好，能够容纳转移人口\r\n","dateStr":"2018-06-12 03:28:05","isPlot":1,"crtDate":"2018-06-11T00:00:00.000Z","crtUser":"admin","picPath":"","status":1,"cDefine1":"","POPULATION":157,"DBVER":"0f20180612032804742","RECORDMAN":"管理员(admin)#&#010-68781602","ZPID":"1507844005070000f01o","WSCD":"WAF150021VBCB000"}},
{"type":"Feature","geometry":{"type":"Point","coordinates":[120.288489,51.495515]},"properties":{"ADCD":"150784103400101","PID":"1507841034001010f01B","NAME":"太平屯安置点2","ADDRESS":"村南","LGTD":120.288489,"LTTD":51.495515,"REMARK":"位于村落南侧，地势较高、平坦开阔，地质条件良好，能够容纳转移人口\r\n","dateStr":"2018-06-12 02:54:06","isPlot":1,"crtDate":"2018-06-11T00:00:00.000Z","crtUser":"admin","picPath":"","status":1,"cDefine1":"","POPULATION":50,"DBVER":"0f20180612025406367","RECORDMAN":"管理员(admin)#&#010-68781602","ZPID":"1507841034001010f01p","WSCD":"WAF1700L00000000"}},
{"type":"Feature","geometry":{"type":"Point","coordinates":[120.097012,50.451476]},"properties":{"ADCD":"150784200005000","PID":"1507844015090000f01C","NAME":"三河第一社区居委会安置点2","ADDRESS":"村南","LGTD":120.097012,"LTTD":50.451476,"REMARK":"位于村落南侧，地势较高、平坦开阔，地质条件良好，能够容纳转移人口\r\n","dateStr":"2018-06-12 03:00:00","isPlot":1,"crtDate":"2018-06-12T00:00:00.000Z","crtUser":"admin","picPath":"","status":1,"cDefine1":"","POPULATION":283,"DBVER":"0f20180612030000492","RECORDMAN":"管理员(admin)#&#010-68781602","ZPID":"1507842000050000f01g","WSCD":"WAF16301IA000000"}},
{"type":"Feature","geometry":{"type":"Point","coordinates":[120.254785,50.673928]},"properties":{"ADCD":"150784401501000","PID":"1507844015010000f01D","NAME":"上护林六队安置点2","ADDRESS":"村东","LGTD":120.254785,"LTTD":50.673928,"REMARK":"位于村落东侧，地势较高、平坦开阔，地质条件良好，能够容纳转移人口\r\n","dateStr":"2018-06-12 03:44:33","isPlot":1,"crtDate":"2018-06-12T00:00:00.000Z","crtUser":"admin","picPath":"","status":1,"cDefine1":"","POPULATION":179,"DBVER":"0f20180612034432838","RECORDMAN":"管理员(admin)#&#010-68781602","ZPID":"1507844015010000f01i","WSCD":"WAF1600R00000000"}},
{"type":"Feature","geometry":{"type":"Point","coordinates":[119.779918,50.471603]},"properties":{"ADCD":"150784403506000","PID":"1507844035060000f01E","NAME":"苏沁牧场安置点2","ADDRESS":"村东","LGTD":119.779918,"LTTD":50.471603,"REMARK":"位于村落东侧，地势较高、平坦开阔，地质条件良好，能够容纳转移人口\r\n","dateStr":"2018-06-12 04:12:17","isPlot":1,"crtDate":"2018-06-12T00:00:00.000Z","crtUser":"admin","picPath":"","status":1,"cDefine1":"","POPULATION":287,"DBVER":"0f20180612041217515","RECORDMAN":"管理员(admin)#&#010-68781602","ZPID":"1507844035060000f01j","WSCD":"WAF1600h00000000"}}
]}